talisman_interfaces-0.11.11.data/data/VERSION
tp_interfaces/__init__.py
tp_interfaces/abstract/__init__.py
tp_interfaces/abstract/exception.py
tp_interfaces/abstract/schema.py
tp_interfaces/abstract/configuration/__init__.py
tp_interfaces/abstract/configuration/factory.py
tp_interfaces/abstract/dataset/__init__.py
tp_interfaces/abstract/dataset/dataset_manager.py
tp_interfaces/abstract/dataset/split_data.py
tp_interfaces/abstract/model/__init__.py
tp_interfaces/abstract/model/composite.py
tp_interfaces/abstract/model/constructable.py
tp_interfaces/abstract/model/merge.py
tp_interfaces/abstract/model/model.py
tp_interfaces/abstract/model/wrapper.py
tp_interfaces/abstract/processor/__init__.py
tp_interfaces/abstract/processor/abstract.py
tp_interfaces/abstract/processor/category.py
tp_interfaces/abstract/processor/exporter.py
tp_interfaces/abstract/processor/message.py
tp_interfaces/abstract/processor/node.py
tp_interfaces/abstract/processor/processor.py
tp_interfaces/abstract/processor/trainer.py
tp_interfaces/abstract/processor/wrapper.py
tp_interfaces/abstract/updatable/__init__.py
tp_interfaces/abstract/updatable/model.py
tp_interfaces/abstract/updatable/update.py
tp_interfaces/abstract/updatable/wrapper.py
tp_interfaces/domain/__init__.py
tp_interfaces/domain/configuration.py
tp_interfaces/domain/filters.py
tp_interfaces/domain/interfaces.py
tp_interfaces/domain/manager.py
tp_interfaces/domain/stub.py
tp_interfaces/domain/value.py
tp_interfaces/domain/abstract/__init__.py
tp_interfaces/domain/abstract/_component.py
tp_interfaces/domain/abstract/_nerc.py
tp_interfaces/domain/abstract/_property.py
tp_interfaces/domain/abstract/_relation.py
tp_interfaces/domain/abstract/_relext.py
tp_interfaces/domain/abstract/_value.py
tp_interfaces/domain/hooks/__init__.py
tp_interfaces/domain/hooks/configuration.py
tp_interfaces/domain/hooks/default_domain.py
tp_interfaces/domain/hooks/tdm_factory.py
tp_interfaces/domain/model/__init__.py
tp_interfaces/domain/model/_model.py
talisman_interfaces-0.11.11.dist-info/METADATA
talisman_interfaces-0.11.11.dist-info/WHEEL
talisman_interfaces-0.11.11.dist-info/top_level.txt
talisman_interfaces-0.11.11.dist-info/RECORD
