Metadata-Version: 2.4
Name: talisman-interfaces
Version: 0.11.11
Summary: Talisman Processor base interfaces
Author: ISPRAS Talisman NLP team
Author-email: modis@ispras.ru
Maintainer: Vladimir Mayorov
Maintainer-email: vmayorov@ispras.ru
License: Apache Software License
Classifier: Development Status :: 3 - Alpha
Classifier: Programming Language :: Python :: 3
Classifier: Programming Language :: Python :: 3.10
Classifier: Intended Audience :: Developers
Classifier: Operating System :: OS Independent
Classifier: License :: OSI Approved :: Apache Software License
Requires-Python: >=3.10
Requires-Dist: talisman-dm<2,>=1.3.10
Requires-Dist: pydantic~=2.5
Requires-Dist: more-itertools>=8.12.0
Requires-Dist: fsspec~=2025.3
Provides-Extra: dvc
Requires-Dist: dvc[s3]>=3.33.3; extra == "dvc"
Dynamic: author
Dynamic: author-email
Dynamic: classifier
Dynamic: description-content-type
Dynamic: license
Dynamic: maintainer
Dynamic: maintainer-email
Dynamic: provides-extra
Dynamic: requires-dist
Dynamic: requires-python
Dynamic: summary
